[
  {
    "name": "kotlin-stdlib",
    "verKey": "kotlinVersion",
    "verName": "Ktlibs Kotlin Stdlib",
    "maven": "https://repo1.maven.org/maven2/org/jetbrains/kotlin/kotlin-stdlib/",
    "minVer": "1.9.10",
    "modrinth": {
      "id": "b06Uh6mW"
    }
  },
  {
    "name": "kotlinx-coroutines-core",
    "verKey": "kotlinxCoroutinesVersion",
    "verName": "Ktlibs Kotlinx Coroutines Core",
    "maven": "https://repo1.maven.org/maven2/org/jetbrains/kotlinx/kotlinx-coroutines-core/maven-metadata.xml",
    "minVer": "1.7.3",
    "modrinth": {
      "id": "3Py6dZNv"
    }
  },
  {
    "name": "kotlinx-serialization",
    "verKey": "kotlinxSerializationVersion",
    "verName": "Ktlibs Kotlinx Serialization",
    "maven": "https://repo1.maven.org/maven2/org/jetbrains/kotlinx/kotlinx-serialization-core/maven-metadata.xml",
    "minVer": "1.6.0",
    "modrinth": {
      "id": "uNWhpnrN"
    }
  }
]
